mltree/__init__.py
mltree/_modidx.py
mltree/train.py
mltree-0.0.2.dist-info/LICENSE
mltree-0.0.2.dist-info/METADATA
mltree-0.0.2.dist-info/WHEEL
mltree-0.0.2.dist-info/entry_points.txt
mltree-0.0.2.dist-info/top_level.txt
mltree-0.0.2.dist-info/RECORD
