Metadata-Version: 2.1
Name: mltree
Version: 0.0.2
Summary: A machine learning package only for tree based models
Home-page: https://github.com/joaopcnogueira/mltree/
Author: João Nogueira
Author-email: joao.nogueira@datarisk.io
License: Apache Software License 2.0
Keywords: nbdev
Platform: UNKNOWN
Classifier: Development Status :: 3 - Alpha
Classifier: Intended Audience :: Developers
Classifier: Natural Language :: English
Classifier: Programming Language :: Python :: 3.8
Classifier: Programming Language :: Python :: 3.9
Classifier: Programming Language :: Python :: 3.10
Classifier: License :: OSI Approved :: Apache Software License
Requires-Python: >=3.8
License-File: LICENSE
Requires-Dist: fastcore
Requires-Dist: feature-engine
Provides-Extra: dev
Requires-Dist: jupyter ; extra == 'dev'
